jsocket/__init__.py
jsocket/_version.py
jsocket/jsocket_base.py
jsocket/tserver.py
jsocket-1.9.6.dist-info/licenses/LICENSE
jsocket-1.9.6.dist-info/METADATA
jsocket-1.9.6.dist-info/WHEEL
jsocket-1.9.6.dist-info/top_level.txt
jsocket-1.9.6.dist-info/RECORD
