Metadata-Version: 2.4
Name: jsocket
Version: 1.9.6
Summary: Python JSON Server & Client
Author-email: Christopher Piekarski <chris@cpiekarski.com>
Maintainer-email: Christopher Piekarski <chris@cpiekarski.com>
License-Expression: Apache-2.0
Project-URL: Homepage, https://cpiekarski.com/2012/01/25/python-json-client-server-redux/
Keywords: json,socket,server,client
Classifier: Intended Audience :: Developers
Classifier: Programming Language :: Python :: 3.9
Classifier: Operating System :: OS Independent
Classifier: Development Status :: 5 - Production/Stable
Classifier: Topic :: System :: Networking
Classifier: Topic :: Software Development :: Libraries :: Application Frameworks
Classifier: Topic :: System :: Distributed Computing
Classifier: Topic :: System :: Hardware :: Symmetric Multi-processing
Requires-Python: >=3.8
License-File: LICENSE
Dynamic: license-file
